Engine/Components.dll
Engine/CoolProp.dll
Engine/CoolPropFluids.csv
Engine/CrankTrain.cp39-win_amd64.pyd
Engine/Cylinder.cp39-win_amd64.pyd
Engine/Cylinder.pyi
Engine/EnginePerform.cp39-win_amd64.pyd
Engine/EnginePerformC.dll
Engine/Environment.cp39-win_amd64.pyd
Engine/Environment.pyi
Engine/Framework.cp39-win_amd64.pyd
Engine/Framework.pyi
Engine/FrameworkC.dll
Engine/GasProperty.cp39-win_amd64.pyd
Engine/GasProperty.pyi
Engine/GasPropertyC.dll
Engine/Injector.cp39-win_amd64.pyd
Engine/Injector.pyi
Engine/Orifice.cp39-win_amd64.pyd
Engine/Pipe.cp39-win_amd64.pyd
Engine/Pipe.pyi
Engine/PyCylinder.py
Engine/PyEnginePerform.py
Engine/PyIntercooler.py
Engine/PyTable.py
Engine/PyTurbocharger.py
Engine/Table.cp39-win_amd64.pyd
Engine/Table.pyi
Engine/TableC.dll
Engine/Tools.dll
Engine/Turbocharger.cp39-win_amd64.pyd
Engine/Turbocharger.pyi
Engine/Valve.cp39-win_amd64.pyd
Engine/Valve.pyi
Engine/Volume.cp39-win_amd64.pyd
Engine/Volume.pyi
Engine/__init__.py
Engine/dllcopy.bat
Engine/engineCUDA.dll
Engine/sqlite3.dll
Engine/Algorithm/FileManipulate.py
Engine/Algorithm/Optimization.py
Engine/Algorithm/__init__.py
Engine/data/Calibrate.xlsm
Engine/data/CylinderPressure.csv
Engine/data/Fuel.db
Engine/data/TurbineMap.xlsx
Engine/data/enginedata.db
Engine/data/enginedata.xlsx
Engine/include/Cylinder.h
Engine/include/MVEM.h
Engine/include/Table.h
Engine/include/Turbocharger.h
Engine/tests/LM.py
Engine/tests/WP7_logfile.txt
Engine/tests/enginedata.xlsx
Engine/tests/fig.svg
Engine/tests/res.json
Engine/tests/single_logfile.txt
Engine/tests/test.py
Engine/tests/testCompressormap.py
Engine/tests/testcombustion.py
Engine/tests/testcompressor.py
Engine/tests/testcrantrain.py
Engine/tests/testcylinderGeo.py
Engine/tests/testcylinderpre.py
Engine/tests/testcylinderpressure.py
Engine/tests/testcylindervalve.py
Engine/tests/testidealcylce.py
Engine/tests/testinjector.py
Engine/tests/testmvem.py
Engine/tests/testnode.py
Engine/tests/testperm.py
Engine/tests/testshocktube.py
pysmartengine-0.0.8.dist-info/LICENSE
pysmartengine-0.0.8.dist-info/METADATA
pysmartengine-0.0.8.dist-info/WHEEL
pysmartengine-0.0.8.dist-info/top_level.txt
pysmartengine-0.0.8.dist-info/RECORD
