Metadata-Version: 2.1
Name: pysmartengine
Version: 0.0.8
Summary: a python library for internal combustion engine
Home-page: https://github.com/melan-thompson/pysmartengine
Author: WenpingXie
Author-email: 1303061669@qq.com
Maintainer: WenpingXie
Classifier: Programming Language :: Python :: 3
Classifier: License :: OSI Approved :: MIT License
Classifier: Operating System :: OS Independent
Classifier: Programming Language :: Python :: 3.9
License-File: LICENSE
Requires-Dist: numpy (>=1.14.4)
Requires-Dist: scipy
Requires-Dist: matplotlib
Requires-Dist: pandas
Requires-Dist: openpyxl
